Workbook

Sheet Summary
A1: NORMA Revenue Model — Month 6 Summary
B3: Conservative | C3: Base Case | D3: Aggressive
A4: Month 6 DAU | B4: =Conservative!G5 -> 404 | C4: ='Base Case'!G5 -> 1525 | D4: =Aggressive!G5 -> 6454
A5: Month 6 MRR | B5: =Conservative!G16 -> 1308 | C5: ='Base Case'!G16 -> 20592 | D5: =Aggressive!G16 -> 182966
A6: Month 6 ARR Run Rate | B6: =Conservative!G28 -> 15696 | C6: ='Base Case'!G28 -> 247104 | D6: =Aggressive!G28 -> 2195592
A7: Month 6 Net Profit | B7: =Conservative!G22 -> 405 | C7: ='Base Case'!G22 -> 19389 | D7: =Aggressive!G22 -> 180763
A8: Cumulative Profit (6mo) | B8: =Conservative!G23 -> 270 | C8: ='Base Case'!G23 -> 68760 | D8: =Aggressive!G23 -> 542120
A9: Month 6 Margin | B9: =Conservative!G24 -> 0.30963303 | C9: ='Base Case'!G24 -> 0.94157925 | D9: =Aggressive!G24 -> 0.98795951
A10: $10K MRR Achieved? | B10: =Conservative!G27 -> No | C10: ='Base Case'!G27 -> YES | D10: =Aggressive!G27 -> YES
A12: Target: $10,000 MRR within 30 days
A13: Adjust blue inputs on the Assumptions tab to model scenarios.

Sheet Assumptions
A1: NORMA Revenue Model — Key Assumptions
A2: All blue values are editable inputs. Black values are calculated.
B4: Conservative | C4: Base Case | D4: Aggressive
A5: USER GROWTH
A6: Month 1 DAU | B6: 200 | C6: 500 | D6: 1200 | F6: Starting daily active users
A7: Monthly DAU Growth Rate | B7: 0.15 | C7: 0.25 | D7: 0.4 | F7: Month-over-month growth
A8: Sessions per User per Day | B8: 1.5 | C8: 2 | D8: 2.5 | F8: App opens per DAU
A9: Moments per Session | B9: 1.2 | C9: 1.8 | D9: 2.5 | F9: Ad-eligible moments per session
A11: AD MONETIZATION
A12: Fill Rate | B12: 0.3 | C12: 0.5 | D12: 0.7 | F12: % of moments with a winning bid
A13: Avg Clearing Price (CPM equiv) | B13: 0.2 | C13: 0.3 | D13: 0.45 | F13: Second-price clearing per impression
A14: Avg CTR | B14: 0.12 | C14: 0.15 | D14: 0.18 | F14: Click-through rate on ad notifications
A15: Max Ads per User per Day | B15: 3 | C15: 3 | D15: 3 | F15: Fatigue cap (fixed)
A17: MONTHLY COSTS
A18: Supabase (Pro) | B18: 25 | C18: 25 | D18: 25 | F18: Database + Edge Functions
A19: Sportradar API | B19: 500 | C19: 500 | D19: 500 | F19: PBP + summary data
A20: SportsDataIO | B20: 100 | C20: 100 | D20: 100 | F20: Schedule data
A21: The Odds API | B21: 50 | C21: 50 | D21: 50 | F21: Odds data
A22: Apple Developer | B22: 8 | C22: 8 | D22: 8 | F22: $99/yr prorated
A23: Domain + Hosting | B23: 20 | C23: 20 | D23: 20 | F23: Vercel + domain
A24: Marketing Spend | B24: 200 | C24: 500 | D24: 1500 | F24: Paid acquisition budget
A25: Total Monthly Costs | B25: =SUM(B18:B24) -> 903 | C25: =SUM(C18:C24) -> 1203 | D25: =SUM(D18:D24) -> 2203

Sheet Conservative
A1: NORMA — Conservative Scenario (6-Month Projection)
B3: Month 1 | C3: Month 2 | D3: Month 3 | E3: Month 4 | F3: Month 5 | G3: Month 6
A4: USER METRICS
A5: Daily Active Users (DAU) | B5: =Assumptions!B6 -> 200 | C5: =ROUND(B5*(1+Assumptions!B7),0) -> 230 | D5: =ROUND(C5*(1+Assumptions!B7),0) -> 265 | E5: =ROUND(D5*(1+Assumptions!B7),0) -> 305 | F5: =ROUND(E5*(1+Assumptions!B7),0) -> 351 | G5: =ROUND(F5*(1+Assumptions!B7),0) -> 404
A6: Sessions per User per Day | B6: =Assumptions!B8 -> 1.5 | C6: =Assumptions!B8 -> 1.5 | D6: =Assumptions!B8 -> 1.5 | E6: =Assumptions!B8 -> 1.5 | F6: =Assumptions!B8 -> 1.5 | G6: =Assumptions!B8 -> 1.5
A7: Total Daily Sessions | B7: =B5*B6 -> 300 | C7: =C5*C6 -> 345 | D7: =D5*D6 -> 397.5 | E7: =E5*E6 -> 457.5 | F7: =F5*F6 -> 526.5 | G7: =G5*G6 -> 606
A8: Moments per Session | B8: =Assumptions!B9 -> 1.2 | C8: =Assumptions!B9 -> 1.2 | D8: =Assumptions!B9 -> 1.2 | E8: =Assumptions!B9 -> 1.2 | F8: =Assumptions!B9 -> 1.2 | G8: =Assumptions!B9 -> 1.2
A9: Total Daily Ad Moments | B9: =MIN(B7*B8, B5*Assumptions!B15) -> 360 | C9: =MIN(C7*C8, C5*Assumptions!B15) -> 414 | D9: =MIN(D7*D8, D5*Assumptions!B15) -> 477 | E9: =MIN(E7*E8, E5*Assumptions!B15) -> 549 | F9: =MIN(F7*F8, F5*Assumptions!B15) -> 631.8 | G9: =MIN(G7*G8, G5*Assumptions!B15) -> 727.2
A11: AD REVENUE
A12: Fill Rate | B12: =Assumptions!B12 -> 0.3 | C12: =Assumptions!B12 -> 0.3 | D12: =Assumptions!B12 -> 0.3 | E12: =Assumptions!B12 -> 0.3 | F12: =Assumptions!B12 -> 0.3 | G12: =Assumptions!B12 -> 0.3
A13: Filled Impressions / Day | B13: =ROUND(B9*B12,0) -> 108 | C13: =ROUND(C9*C12,0) -> 124 | D13: =ROUND(D9*D12,0) -> 143 | E13: =ROUND(E9*E12,0) -> 165 | F13: =ROUND(F9*F12,0) -> 190 | G13: =ROUND(G9*G12,0) -> 218
A14: Avg Clearing Price | B14: =Assumptions!B13 -> 0.2 | C14: =Assumptions!B13 -> 0.2 | D14: =Assumptions!B13 -> 0.2 | E14: =Assumptions!B13 -> 0.2 | F14: =Assumptions!B13 -> 0.2 | G14: =Assumptions!B13 -> 0.2
A15: Daily Ad Revenue | B15: =B13*B14 -> 21.6 | C15: =C13*C14 -> 24.8 | D15: =D13*D14 -> 28.6 | E15: =E13*E14 -> 33 | F15: =F13*F14 -> 38 | G15: =G13*G14 -> 43.6
A16: Monthly Ad Revenue (MRR) | B16: =ROUND(B15*30,0) -> 648 | C16: =ROUND(C15*30,0) -> 744 | D16: =ROUND(D15*30,0) -> 858 | E16: =ROUND(E15*30,0) -> 990 | F16: =ROUND(F15*30,0) -> 1140 | G16: =ROUND(G15*30,0) -> 1308
A18: COSTS
A19: Total Monthly Costs | B19: =Assumptions!B25 -> 903 | C19: =Assumptions!B25 -> 903 | D19: =Assumptions!B25 -> 903 | E19: =Assumptions!B25 -> 903 | F19: =Assumptions!B25 -> 903 | G19: =Assumptions!B25 -> 903
A21: BOTTOM LINE
A22: Net Monthly Profit / (Loss) | B22: =B16-B19 -> -255 | C22: =C16-C19 -> -159 | D22: =D16-D19 -> -45 | E22: =E16-E19 -> 87 | F22: =F16-F19 -> 237 | G22: =G16-G19 -> 405
A23: Cumulative Profit / (Loss) | B23: =B22 -> -255 | C23: =B23+C22 -> -414 | D23: =C23+D22 -> -459 | E23: =D23+E22 -> -372 | F23: =E23+F22 -> -135 | G23: =F23+G22 -> 270
A24: Margin % | B24: =IF(B16=0,0,B22/B16) -> -0.39351852 | C24: =IF(C16=0,0,C22/C16) -> -0.21370968 | D24: =IF(D16=0,0,D22/D16) -> -0.052447552 | E24: =IF(E16=0,0,E22/E16) -> 0.087878788 | F24: =IF(F16=0,0,F22/F16) -> 0.20789474 | G24: =IF(G16=0,0,G22/G16) -> 0.30963303
A26: KEY MILESTONES
A27: $10K MRR Target Hit? | B27: =IF(B16>=10000,"YES","No") -> No | C27: =IF(C16>=10000,"YES","No") -> No | D27: =IF(D16>=10000,"YES","No") -> No | E27: =IF(E16>=10000,"YES","No") -> No | F27: =IF(F16>=10000,"YES","No") -> No | G27: =IF(G16>=10000,"YES","No") -> No
A28: ARR Run Rate | B28: =B16*12 -> 7776 | C28: =C16*12 -> 8928 | D28: =D16*12 -> 10296 | E28: =E16*12 -> 11880 | F28: =F16*12 -> 13680 | G28: =G16*12 -> 15696
A29: Monthly Impressions | B29: =B13*30 -> 3240 | C29: =C13*30 -> 3720 | D29: =D13*30 -> 4290 | E29: =E13*30 -> 4950 | F29: =F13*30 -> 5700 | G29: =G13*30 -> 6540

Sheet Base Case
A1: NORMA — Base Case Scenario (6-Month Projection)
B3: Month 1 | C3: Month 2 | D3: Month 3 | E3: Month 4 | F3: Month 5 | G3: Month 6
A4: USER METRICS
A5: Daily Active Users (DAU) | B5: =Assumptions!C6 -> 500 | C5: =ROUND(B5*(1+Assumptions!C7),0) -> 625 | D5: =ROUND(C5*(1+Assumptions!C7),0) -> 781 | E5: =ROUND(D5*(1+Assumptions!C7),0) -> 976 | F5: =ROUND(E5*(1+Assumptions!C7),0) -> 1220 | G5: =ROUND(F5*(1+Assumptions!C7),0) -> 1525
A6: Sessions per User per Day | B6: =Assumptions!C8 -> 2 | C6: =Assumptions!C8 -> 2 | D6: =Assumptions!C8 -> 2 | E6: =Assumptions!C8 -> 2 | F6: =Assumptions!C8 -> 2 | G6: =Assumptions!C8 -> 2
A7: Total Daily Sessions | B7: =B5*B6 -> 1000 | C7: =C5*C6 -> 1250 | D7: =D5*D6 -> 1562 | E7: =E5*E6 -> 1952 | F7: =F5*F6 -> 2440 | G7: =G5*G6 -> 3050
A8: Moments per Session | B8: =Assumptions!C9 -> 1.8 | C8: =Assumptions!C9 -> 1.8 | D8: =Assumptions!C9 -> 1.8 | E8: =Assumptions!C9 -> 1.8 | F8: =Assumptions!C9 -> 1.8 | G8: =Assumptions!C9 -> 1.8
A9: Total Daily Ad Moments | B9: =MIN(B7*B8, B5*Assumptions!C15) -> 1500 | C9: =MIN(C7*C8, C5*Assumptions!C15) -> 1875 | D9: =MIN(D7*D8, D5*Assumptions!C15) -> 2343 | E9: =MIN(E7*E8, E5*Assumptions!C15) -> 2928 | F9: =MIN(F7*F8, F5*Assumptions!C15) -> 3660 | G9: =MIN(G7*G8, G5*Assumptions!C15) -> 4575
A11: AD REVENUE
A12: Fill Rate | B12: =Assumptions!C12 -> 0.5 | C12: =Assumptions!C12 -> 0.5 | D12: =Assumptions!C12 -> 0.5 | E12: =Assumptions!C12 -> 0.5 | F12: =Assumptions!C12 -> 0.5 | G12: =Assumptions!C12 -> 0.5
A13: Filled Impressions / Day | B13: =ROUND(B9*B12,0) -> 750 | C13: =ROUND(C9*C12,0) -> 938 | D13: =ROUND(D9*D12,0) -> 1172 | E13: =ROUND(E9*E12,0) -> 1464 | F13: =ROUND(F9*F12,0) -> 1830 | G13: =ROUND(G9*G12,0) -> 2288
A14: Avg Clearing Price | B14: =Assumptions!C13 -> 0.3 | C14: =Assumptions!C13 -> 0.3 | D14: =Assumptions!C13 -> 0.3 | E14: =Assumptions!C13 -> 0.3 | F14: =Assumptions!C13 -> 0.3 | G14: =Assumptions!C13 -> 0.3
A15: Daily Ad Revenue | B15: =B13*B14 -> 225 | C15: =C13*C14 -> 281.4 | D15: =D13*D14 -> 351.6 | E15: =E13*E14 -> 439.2 | F15: =F13*F14 -> 549 | G15: =G13*G14 -> 686.4
A16: Monthly Ad Revenue (MRR) | B16: =ROUND(B15*30,0) -> 6750 | C16: =ROUND(C15*30,0) -> 8442 | D16: =ROUND(D15*30,0) -> 10548 | E16: =ROUND(E15*30,0) -> 13176 | F16: =ROUND(F15*30,0) -> 16470 | G16: =ROUND(G15*30,0) -> 20592
A18: COSTS
A19: Total Monthly Costs | B19: =Assumptions!C25 -> 1203 | C19: =Assumptions!C25 -> 1203 | D19: =Assumptions!C25 -> 1203 | E19: =Assumptions!C25 -> 1203 | F19: =Assumptions!C25 -> 1203 | G19: =Assumptions!C25 -> 1203
A21: BOTTOM LINE
A22: Net Monthly Profit / (Loss) | B22: =B16-B19 -> 5547 | C22: =C16-C19 -> 7239 | D22: =D16-D19 -> 9345 | E22: =E16-E19 -> 11973 | F22: =F16-F19 -> 15267 | G22: =G16-G19 -> 19389
A23: Cumulative Profit / (Loss) | B23: =B22 -> 5547 | C23: =B23+C22 -> 12786 | D23: =C23+D22 -> 22131 | E23: =D23+E22 -> 34104 | F23: =E23+F22 -> 49371 | G23: =F23+G22 -> 68760
A24: Margin % | B24: =IF(B16=0,0,B22/B16) -> 0.82177778 | C24: =IF(C16=0,0,C22/C16) -> 0.85749822 | D24: =IF(D16=0,0,D22/D16) -> 0.88594994 | E24: =IF(E16=0,0,E22/E16) -> 0.90869763 | F24: =IF(F16=0,0,F22/F16) -> 0.92695811 | G24: =IF(G16=0,0,G22/G16) -> 0.94157925
A26: KEY MILESTONES
A27: $10K MRR Target Hit? | B27: =IF(B16>=10000,"YES","No") -> No | C27: =IF(C16>=10000,"YES","No") -> No | D27: =IF(D16>=10000,"YES","No") -> YES | E27: =IF(E16>=10000,"YES","No") -> YES | F27: =IF(F16>=10000,"YES","No") -> YES | G27: =IF(G16>=10000,"YES","No") -> YES
A28: ARR Run Rate | B28: =B16*12 -> 81000 | C28: =C16*12 -> 101304 | D28: =D16*12 -> 126576 | E28: =E16*12 -> 158112 | F28: =F16*12 -> 197640 | G28: =G16*12 -> 247104
A29: Monthly Impressions | B29: =B13*30 -> 22500 | C29: =C13*30 -> 28140 | D29: =D13*30 -> 35160 | E29: =E13*30 -> 43920 | F29: =F13*30 -> 54900 | G29: =G13*30 -> 68640

Sheet Aggressive
A1: NORMA — Aggressive Scenario (6-Month Projection)
B3: Month 1 | C3: Month 2 | D3: Month 3 | E3: Month 4 | F3: Month 5 | G3: Month 6
A4: USER METRICS
A5: Daily Active Users (DAU) | B5: =Assumptions!D6 -> 1200 | C5: =ROUND(B5*(1+Assumptions!D7),0) -> 1680 | D5: =ROUND(C5*(1+Assumptions!D7),0) -> 2352 | E5: =ROUND(D5*(1+Assumptions!D7),0) -> 3293 | F5: =ROUND(E5*(1+Assumptions!D7),0) -> 4610 | G5: =ROUND(F5*(1+Assumptions!D7),0) -> 6454
A6: Sessions per User per Day | B6: =Assumptions!D8 -> 2.5 | C6: =Assumptions!D8 -> 2.5 | D6: =Assumptions!D8 -> 2.5 | E6: =Assumptions!D8 -> 2.5 | F6: =Assumptions!D8 -> 2.5 | G6: =Assumptions!D8 -> 2.5
A7: Total Daily Sessions | B7: =B5*B6 -> 3000 | C7: =C5*C6 -> 4200 | D7: =D5*D6 -> 5880 | E7: =E5*E6 -> 8232.5 | F7: =F5*F6 -> 11525 | G7: =G5*G6 -> 16135
A8: Moments per Session | B8: =Assumptions!D9 -> 2.5 | C8: =Assumptions!D9 -> 2.5 | D8: =Assumptions!D9 -> 2.5 | E8: =Assumptions!D9 -> 2.5 | F8: =Assumptions!D9 -> 2.5 | G8: =Assumptions!D9 -> 2.5
A9: Total Daily Ad Moments | B9: =MIN(B7*B8, B5*Assumptions!D15) -> 3600 | C9: =MIN(C7*C8, C5*Assumptions!D15) -> 5040 | D9: =MIN(D7*D8, D5*Assumptions!D15) -> 7056 | E9: =MIN(E7*E8, E5*Assumptions!D15) -> 9879 | F9: =MIN(F7*F8, F5*Assumptions!D15) -> 13830 | G9: =MIN(G7*G8, G5*Assumptions!D15) -> 19362
A11: AD REVENUE
A12: Fill Rate | B12: =Assumptions!D12 -> 0.7 | C12: =Assumptions!D12 -> 0.7 | D12: =Assumptions!D12 -> 0.7 | E12: =Assumptions!D12 -> 0.7 | F12: =Assumptions!D12 -> 0.7 | G12: =Assumptions!D12 -> 0.7
A13: Filled Impressions / Day | B13: =ROUND(B9*B12,0) -> 2520 | C13: =ROUND(C9*C12,0) -> 3528 | D13: =ROUND(D9*D12,0) -> 4939 | E13: =ROUND(E9*E12,0) -> 6915 | F13: =ROUND(F9*F12,0) -> 9681 | G13: =ROUND(G9*G12,0) -> 13553
A14: Avg Clearing Price | B14: =Assumptions!D13 -> 0.45 | C14: =Assumptions!D13 -> 0.45 | D14: =Assumptions!D13 -> 0.45 | E14: =Assumptions!D13 -> 0.45 | F14: =Assumptions!D13 -> 0.45 | G14: =Assumptions!D13 -> 0.45
A15: Daily Ad Revenue | B15: =B13*B14 -> 1134 | C15: =C13*C14 -> 1587.6 | D15: =D13*D14 -> 2222.55 | E15: =E13*E14 -> 3111.75 | F15: =F13*F14 -> 4356.45 | G15: =G13*G14 -> 6098.85
A16: Monthly Ad Revenue (MRR) | B16: =ROUND(B15*30,0) -> 34020 | C16: =ROUND(C15*30,0) -> 47628 | D16: =ROUND(D15*30,0) -> 66677 | E16: =ROUND(E15*30,0) -> 93353 | F16: =ROUND(F15*30,0) -> 130694 | G16: =ROUND(G15*30,0) -> 182966
A18: COSTS
A19: Total Monthly Costs | B19: =Assumptions!D25 -> 2203 | C19: =Assumptions!D25 -> 2203 | D19: =Assumptions!D25 -> 2203 | E19: =Assumptions!D25 -> 2203 | F19: =Assumptions!D25 -> 2203 | G19: =Assumptions!D25 -> 2203
A21: BOTTOM LINE
A22: Net Monthly Profit / (Loss) | B22: =B16-B19 -> 31817 | C22: =C16-C19 -> 45425 | D22: =D16-D19 -> 64474 | E22: =E16-E19 -> 91150 | F22: =F16-F19 -> 128491 | G22: =G16-G19 -> 180763
A23: Cumulative Profit / (Loss) | B23: =B22 -> 31817 | C23: =B23+C22 -> 77242 | D23: =C23+D22 -> 141716 | E23: =D23+E22 -> 232866 | F23: =E23+F22 -> 361357 | G23: =F23+G22 -> 542120
A24: Margin % | B24: =IF(B16=0,0,B22/B16) -> 0.93524397 | C24: =IF(C16=0,0,C22/C16) -> 0.9537457 | D24: =IF(D16=0,0,D22/D16) -> 0.96696012 | E24: =IF(E16=0,0,E22/E16) -> 0.9764014 | F24: =IF(F16=0,0,F22/F16) -> 0.98314383 | G24: =IF(G16=0,0,G22/G16) -> 0.98795951
A26: KEY MILESTONES
A27: $10K MRR Target Hit? | B27: =IF(B16>=10000,"YES","No") -> YES | C27: =IF(C16>=10000,"YES","No") -> YES | D27: =IF(D16>=10000,"YES","No") -> YES | E27: =IF(E16>=10000,"YES","No") -> YES | F27: =IF(F16>=10000,"YES","No") -> YES | G27: =IF(G16>=10000,"YES","No") -> YES
A28: ARR Run Rate | B28: =B16*12 -> 408240 | C28: =C16*12 -> 571536 | D28: =D16*12 -> 800124 | E28: =E16*12 -> 1120236 | F28: =F16*12 -> 1568328 | G28: =G16*12 -> 2195592
A29: Monthly Impressions | B29: =B13*30 -> 75600 | C29: =C13*30 -> 105840 | D29: =D13*30 -> 148170 | E29: =E13*30 -> 207450 | F29: =F13*30 -> 290430 | G29: =G13*30 -> 406590
